Metadata-Version: 2.1
Name: py-automl
Version: 1.0.6
Summary: py-automl - An open source, low-code machine learning library in Python.
Home-page: https://github.com/PrudhviGNV/py-automl
Author: Prudhvi GNV
Author-email: prudhvi.gnv@gmail.com
License: MIT
Platform: UNKNOWN
Classifier: License :: OSI Approved :: MIT License
Classifier: Programming Language :: Python :: 3.6
Classifier: Programming Language :: Python :: 3.7
Classifier: Programming Language :: Python :: 3.8
